kafka_rest/__init__.py
kafka_rest/kafka_rest.py
kafka_rest/snippets/__init__.py
kafka_rest/snippets/snippet_consumer_step_calls.py
kafka_rest/snippets/snippet_producer_consumer.py
kafka_rest/snippets/snippet_producer_files.py
nlp_kafka_rest_api-1.0.0.dist-info/LICENSE
nlp_kafka_rest_api-1.0.0.dist-info/METADATA
nlp_kafka_rest_api-1.0.0.dist-info/WHEEL
nlp_kafka_rest_api-1.0.0.dist-info/entry_points.txt
nlp_kafka_rest_api-1.0.0.dist-info/top_level.txt
nlp_kafka_rest_api-1.0.0.dist-info/RECORD
