Metadata-Version: 2.1
Name: nlp-kafka-rest-api
Version: 1.0.0
Summary: This package is a wrapper for REST API requests to Kafka Proxy.
License: Copyright (c) 2023 Merck KGaA, Darmstadt, Germany
Keywords: nlp,kafka,rest,proxy
Classifier: License :: OSI Approved :: MIT License
Classifier: Programming Language :: Python
Classifier: Programming Language :: Python :: 3
Requires-Python: >=3.6
License-File: LICENSE
Requires-Dist: requests
Provides-Extra: dev
Requires-Dist: pip-tools ; extra == 'dev'
